pymoca/Modelica.g4
pymoca/__init__.py
pymoca/_version.py
pymoca/ast.py
pymoca/parser.py
pymoca/tree.py
pymoca/backends/__init__.py
pymoca/backends/casadi/__init__.py
pymoca/backends/casadi/_options.py
pymoca/backends/casadi/alias_relation.py
pymoca/backends/casadi/api.py
pymoca/backends/casadi/generator.py
pymoca/backends/casadi/model.py
pymoca/backends/casadi/mtensor.py
pymoca/backends/sympy/__init__.py
pymoca/backends/sympy/generator.py
pymoca/backends/sympy/runtime.py
pymoca/backends/xml/__init__.py
pymoca/backends/xml/analysis.py
pymoca/backends/xml/generator.py
pymoca/backends/xml/model.py
pymoca/backends/xml/parser.py
pymoca/backends/xml/sim_scipy.py
pymoca/backends/xml/ModelicaXML/schemas/Equation_Statement_separate.xsd
pymoca/backends/xml/ModelicaXML/schemas/Expression.xsd
pymoca/backends/xml/ModelicaXML/schemas/Modelica.xsd
pymoca/backends/xml/ModelicaXML/schemas/Types.xsd
pymoca/generated/ModelicaLexer.py
pymoca/generated/ModelicaListener.py
pymoca/generated/ModelicaParser.py
pymoca/generated/ModelicaVisitor.py
pymoca/generated/__init__.py
pymoca-0.11.1.dist-info/LICENSE
pymoca-0.11.1.dist-info/METADATA
pymoca-0.11.1.dist-info/WHEEL
pymoca-0.11.1.dist-info/top_level.txt
pymoca-0.11.1.dist-info/RECORD
