Metadata-Version: 2.2
Name: pymoca
Version: 0.11.1
Summary: A Modelica to computer algebra system (CAS) translator.
Author: Pymoca Contributors
Maintainer-email: Jack Vreeken <jack@vreeken.me>, Kent Rutan <gs1150e@icloud.com>
License: Copyright (c) 2016-2021, James Goppert and the Pymoca contributors.
Project-URL: homepage, https://github.com/pymoca/pymoca
Keywords: modelica,simulation,compiler
Classifier: Development Status :: 3 - Alpha
Classifier: Intended Audience :: Science/Research
Classifier: Intended Audience :: Developers
Classifier: License :: OSI Approved :: BSD License
Classifier: Programming Language :: Python
Classifier: Programming Language :: Python :: 3
Classifier: Programming Language :: Other
Classifier: Topic :: Software Development
Classifier: Topic :: Scientific/Engineering :: Artificial Intelligence
Classifier: Topic :: Scientific/Engineering :: Mathematics
Classifier: Topic :: Scientific/Engineering :: Physics
Classifier: Topic :: Scientific/Engineering :: Visualization
Classifier: Operating System :: Microsoft :: Windows
Classifier: Operating System :: POSIX
Classifier: Operating System :: Unix
Classifier: Operating System :: MacOS
Classifier: Topic :: Software Development :: Code Generators
Classifier: Topic :: Software Development :: Compilers
Classifier: Topic :: Software Development :: Embedded Systems
Requires-Python: >=3.9
License-File: LICENSE
Requires-Dist: numpy>=1.8.2
Requires-Dist: antlr4-python3-runtime==4.13.*
Provides-Extra: casadi
Requires-Dist: casadi>=3.4.0; extra == "casadi"
Requires-Dist: setuptools>=60.0.0; extra == "casadi"
Provides-Extra: lxml
Requires-Dist: lxml>=3.5.0; extra == "lxml"
Requires-Dist: scipy>=0.13.3; extra == "lxml"
Provides-Extra: sympy
Requires-Dist: sympy>=0.7.6.1; extra == "sympy"
Requires-Dist: scipy>=0.13.3; extra == "sympy"
Requires-Dist: jinja2>=2.10.1; extra == "sympy"
Provides-Extra: examples
Requires-Dist: jupyterlab; extra == "examples"
Requires-Dist: matplotlib; extra == "examples"
Requires-Dist: control<=0.10.0,>=0.9.3.post2; extra == "examples"
Provides-Extra: all
Requires-Dist: pymoca[casadi,examples,lxml,sympy]; extra == "all"
